MANIFEST.in
README.rst
setup.py
batbelt/__init__.py
batbelt/hack.py
batbelt/objects.py
batbelt/parallel.py
batbelt/strings.py
batbelt/structs.py
batbelt/utils.py
batbelt.egg-info/PKG-INFO
batbelt.egg-info/SOURCES.txt
batbelt.egg-info/dependency_links.txt
batbelt.egg-info/top_level.txt