Metadata-Version: 1.1
Name: batbelt
Version: 0.5
Summary: A collection of gagdets that makes Python even more powerful.
Home-page: https://github.com/sametmax/Bat-belt
Author: Sam et Max
Author-email: lesametlemax@gmail.com
License: UNKNOWN
Platform: UNKNOWN
Classifier: Programming Language :: Python
Classifier: Intended Audience :: Information Technology
Classifier: License :: OSI Approved :: zlib/libpng License
Classifier: Natural Language :: English
Classifier: Programming Language :: Python :: 2.7
